nlweb_elastic_vectordb/__init__.py
nlweb_elastic_vectordb/elasticsearch_client.py
nlweb_elastic_vectordb/elasticsearch_writer.py
nlweb_elastic_vectordb-0.5.42.dist-info/METADATA
nlweb_elastic_vectordb-0.5.42.dist-info/WHEEL
nlweb_elastic_vectordb-0.5.42.dist-info/top_level.txt
nlweb_elastic_vectordb-0.5.42.dist-info/RECORD
