Metadata-Version: 2.4
Name: nlweb-elastic-vectordb
Version: 0.5.42
Summary: Elasticsearch provider for NLWeb - third-party vector database provider
Author: Microsoft Corporation
License: MIT
Project-URL: Homepage, https://github.com/microsoft/NLWeb_Core
Project-URL: Repository, https://github.com/microsoft/NLWeb_Core
Project-URL: Issues, https://github.com/microsoft/NLWeb_Core/issues
Classifier: Development Status :: 4 - Beta
Classifier: Intended Audience :: Developers
Classifier: License :: OSI Approved :: MIT License
Classifier: Programming Language :: Python :: 3
Classifier: Programming Language :: Python :: 3.9
Classifier: Programming Language :: Python :: 3.10
Classifier: Programming Language :: Python :: 3.11
Classifier: Programming Language :: Python :: 3.12
Requires-Python: >=3.9
Requires-Dist: nlweb-core>=0.5.42
Requires-Dist: elasticsearch>=8.0.0
Provides-Extra: dev
Requires-Dist: pytest>=7.0; extra == "dev"
Requires-Dist: pytest-asyncio>=0.21.0; extra == "dev"
Requires-Dist: pytest-cov>=4.0.0; extra == "dev"
Requires-Dist: pytest-mock>=3.10.0; extra == "dev"
